stts75m2f/__init__.py
stts75m2f/stts75m2f.py
tests/__init__.py
tests/test_stts75m2f_real.py
stts75m2f-0.6.dist-info/METADATA
stts75m2f-0.6.dist-info/WHEEL
stts75m2f-0.6.dist-info/top_level.txt
stts75m2f-0.6.dist-info/RECORD
