Metadata-Version: 2.1
Name: stts75m2f
Version: 0.6
Summary: Pythona library for STTS75M2F temperature sensor
Home-page: https://github.com/darton/stts75m2f
Author: Dariusz Kowalczyk
Author-email: darton.dariusz.kowalczyk@gmail.com
License: UNKNOWN
Platform: UNKNOWN
Classifier: Programming Language :: Python :: 3
Classifier: License :: OSI Approved :: MIT License
Classifier: Operating System :: OS Independent
Requires-Python: >=3.6
Requires-Dist: smbus2
